project/__init__.py
project/asgi.py
project/settings.py
project/urls.py
project/wsgi.py
template_email_manager/__init__.py
template_email_manager/admin.py
template_email_manager/apps.py
template_email_manager/commands.py
template_email_manager/manager.py
template_email_manager/models.py
template_email_manager/tasks.py
template_email_manager/tests.py
template_email_manager/urls.py
template_email_manager/views.py
template_email_manager/migrations/0001_initial.py
template_email_manager/migrations/__init__.py
django_template_email_manager-0.1.0.dist-info/LICENSE
django_template_email_manager-0.1.0.dist-info/METADATA
django_template_email_manager-0.1.0.dist-info/WHEEL
django_template_email_manager-0.1.0.dist-info/top_level.txt
django_template_email_manager-0.1.0.dist-info/RECORD
