Metadata-Version: 2.1
Name: django-template-email-manager
Version: 0.1.0
Summary: A small useful app to manage email queues with customizable templates from any django project
Home-page: https://github.com/mbacicc/django-template-email-manager
Author: mbacicc
Author-email: mbacicc@gmail.com
License: MIT
Platform: UNKNOWN
Requires-Python: >=3.6
Requires-Dist: django
